teambition/__init__.py
teambition/client.py
teambition/exceptions.py
teambition/utils.py
teambition/api/__init__.py
teambition/api/activities.py
teambition/api/base.py
teambition/api/bookkeepings.py
teambition/api/collections.py
teambition/api/entries.py
teambition/api/entrycategories.py
teambition/api/events.py
teambition/api/messages.py
teambition/api/oauth.py
teambition/api/objectlinks.py
teambition/api/organizations.py
teambition/api/posts.py
teambition/api/projects.py
teambition/api/stages.py
teambition/api/stagetemplates.py
teambition/api/subtasks.py
teambition/api/tags.py
teambition/api/tasklists.py
teambition/api/tasks.py
teambition/api/teams.py
teambition/api/users.py
teambition/api/webhooks.py
teambition/api/works.py
teambition-0.2.0.dist-info/DESCRIPTION.rst
teambition-0.2.0.dist-info/METADATA
teambition-0.2.0.dist-info/RECORD
teambition-0.2.0.dist-info/WHEEL
teambition-0.2.0.dist-info/metadata.json
teambition-0.2.0.dist-info/pbr.json
teambition-0.2.0.dist-info/top_level.txt
