Metadata-Version: 2.0
Name: teambition
Version: 0.2.0
Summary: Teambition Python API
Home-page: https://github.com/messense/teambition-api
Author: messense
Author-email: messense@icloud.com
License: UNKNOWN
Keywords: Teambition,SDK
Platform: UNKNOWN
Classifier: Development Status :: 4 - Beta
Classifier: License :: OSI Approved :: MIT License
Classifier: Operating System :: MacOS
Classifier: Operating System :: POSIX
Classifier: Operating System :: POSIX :: Linux
Classifier: Programming Language :: Python
Classifier: Programming Language :: Python :: 2.6
Classifier: Programming Language :: Python :: 2.7
Classifier: Programming Language :: Python :: 3.2
Classifier: Programming Language :: Python :: 3.3
Classifier: Programming Language :: Python :: 3.4
Classifier: Programming Language :: Python :: Implementation :: CPython
Classifier: Programming Language :: Python :: Implementation :: PyPy
Classifier: Intended Audience :: Developers
Classifier: Topic :: Software Development :: Libraries
Classifier: Topic :: Software Development :: Libraries :: Python Modules
Classifier: Topic :: Utilities
Requires-Dist: furl (>=0.4.6)
Requires-Dist: optionaldict (>=0.1.0)
Requires-Dist: python-dateutil (>=2.4.2)
Requires-Dist: pytz (>=2015.4)
Requires-Dist: requests (>=2.7.0)
Requires-Dist: six (>=1.8.0)
